justextnext
